Metadata-Version: 2.1
Name: metapi
Version: 2.4.0
Summary: a pipeline to construct a genome catalogue from metagenomics data
Home-page: https://github.com/ohmeta/metapi
Author: Jie Zhu, Fangming Yang
Author-email: alienchuj@gmail.com
License: GPLv3+
Classifier: Development Status :: 3 - Alpha
Classifier: Environment :: Console
Classifier: Intended Audience :: Developers
Classifier: Intended Audience :: Science/Research
Classifier: License :: OSI Approved :: GNU General Public License v3 (GPLv3)
Classifier: Natural Language :: English
Classifier: Operating System :: OS Independent
Classifier: Programming Language :: Python :: 3.7
Classifier: Programming Language :: Python :: 3.8
Classifier: Programming Language :: Python :: 3.9
Classifier: Programming Language :: Python :: 3.10
Classifier: Topic :: Scientific/Engineering :: Bio-Informatics
License-File: LICENSE
Requires-Dist: numpy
Requires-Dist: pandas
Requires-Dist: openpyxl
Requires-Dist: snakemake (>=7.0)
Requires-Dist: ruamel.yaml
Requires-Dist: natsort
Requires-Dist: biopython (>=1.73)
Requires-Dist: seaborn
Requires-Dist: matplotlib
